{
		"Contact Details": "Scottish Government ",
		"Data type": ", XLS",
		"Description": "Affordable Housing Supply Programme split by social rent, other affordable rent and affordable home ownership",
		"Dimensions": "",
		"Family": "Affordable Housing",
		"Frequency": "Quarterly",
		"Landing Page": "https://www2.gov.scot/Topics/Statistics/Browse/Housing-Regeneration",
		"Last Published": "2019-09-24",
		"Name": "Affordable Housing Supply (Scot Gov)",
		"Next Due": "",
		"Notes": "",
		"PMD v3 publication": "",
		"Producer": "Scottish Government (SG)",
		"Route from landing page to data": "Data can be located by scrolling to the 'Quarterly Housing Update'  table and clicking on the 'Excel tables - Affordable Housing Supply Programme approvals, starts and completions by social rent, affordable rent, and affordable home ownership and by new build'.  Locate the data in file.",
		"Size": "Medium",
		"Sizing Notes": "Straightforward table structure though some work required on mixed dimensions to enable extraction.  A bit of messiness from a couple footnote markers.",
		"Stage": "Prioritized",
		"Stakeholder Engagement notes": "",
		"transform": {
				"main_issue":98
		}
}